[
  {
    "username": "lnthuong1",
    "password": "12345678"
  },
  {
    "username": "lnthuong2",
    "password": "12345678"
  },
  {
    "username": "lnthuong3",
    "password": "12345678"
  },
  {
    "username": "lnthuong4",
    "password": "12345678"
  },
  {
    "username": "lnthuong5",
    "password": "12345678"
  },
  {
    "username": "lnthuong6",
    "password": "12345678"
  },
  {
    "username": "lnthuong7",
    "password": "12345678"
  },
  {
    "username": "lnthuong8",
    "password": "12345678"
  },
  {
    "username": "lnthuong9",
    "password": "12345678"
  },
  {
    "username": "lnthuong10",
    "password": "12345678"
  }
]